codam/__init__.py
codam/svm.py
codam/svm_extension.cpython-39-x86_64-linux-gnu.so
codam-0.1.0.dist-info/METADATA
codam-0.1.0.dist-info/WHEEL
codam-0.1.0.dist-info/top_level.txt
codam-0.1.0.dist-info/RECORD
